odoo8_addon_crm_claim_phone-8.0.0.1.0.99.dev9-py2.7-nspkg.pth
odoo8_addon_crm_claim_phone-8.0.0.1.0.99.dev9.dist-info/METADATA
odoo8_addon_crm_claim_phone-8.0.0.1.0.99.dev9.dist-info/RECORD
odoo8_addon_crm_claim_phone-8.0.0.1.0.99.dev9.dist-info/WHEEL
odoo8_addon_crm_claim_phone-8.0.0.1.0.99.dev9.dist-info/namespace_packages.txt
odoo8_addon_crm_claim_phone-8.0.0.1.0.99.dev9.dist-info/top_level.txt
odoo_addons/crm_claim_phone/__init__.py
odoo_addons/crm_claim_phone/__openerp__.py
odoo_addons/crm_claim_phone/crm_claim_phone.py
odoo_addons/crm_claim_phone/crm_claim_view.xml
odoo_addons/crm_claim_phone/i18n/bg.po
odoo_addons/crm_claim_phone/i18n/crm_claim_phone.pot
odoo_addons/crm_claim_phone/i18n/de.po
odoo_addons/crm_claim_phone/i18n/es.po
odoo_addons/crm_claim_phone/i18n/fr.po
odoo_addons/crm_claim_phone/i18n/nb.po
odoo_addons/crm_claim_phone/i18n/pt_BR.po
odoo_addons/crm_claim_phone/i18n/sk.po
odoo_addons/crm_claim_phone/i18n/sl.po
odoo_addons/crm_claim_phone/i18n/sv.po
odoo_addons/crm_claim_phone/i18n/tr.po
odoo_addons/crm_claim_phone/i18n/zh_CN.po
odoo_addons/crm_claim_phone/static/description/icon.png
